sqlalchemy_lazy_way/__init__.py
sqlalchemy_lazy_way/smart_query.py
sqlalchemy_lazy_way-0.0.1.dist-info/WHEEL
sqlalchemy_lazy_way-0.0.1.dist-info/METADATA
sqlalchemy_lazy_way-0.0.1.dist-info/RECORD
