Metadata-Version: 2.1
Name: sqlalchemy-lazy-way
Version: 0.0.1
Summary: sqlalchemy-lazy-way 
Home-page: https://github.com/twocucao/sqlalchemy-lazy-way
License: MIT
Keywords: sqlalchemy-lazy-way
Author: twocucao
Author-email: twocucao@gmail.com
Requires-Python: >=3.7,<4.0
Classifier: License :: OSI Approved :: MIT License
Classifier: Programming Language :: Python :: 3
Classifier: Programming Language :: Python :: 3.7
Requires-Dist: sqlalchemy (>=1.2,<2.0)
Project-URL: Repository, https://github.com/twocucao/sqlalchemy-lazy-way
